flask_fixtures/__init__.py
flask_fixtures/loaders.py
flask_fixtures/utils.py
Flask_YAML_Fixtures-0.5.1.dist-info/LICENSE
Flask_YAML_Fixtures-0.5.1.dist-info/METADATA
Flask_YAML_Fixtures-0.5.1.dist-info/WHEEL
Flask_YAML_Fixtures-0.5.1.dist-info/top_level.txt
Flask_YAML_Fixtures-0.5.1.dist-info/RECORD
