Metadata-Version: 2.1
Name: Flask-YAML-Fixtures
Version: 0.5.1
Summary: A simple library for adding database fixtures for unit tests using nothing but JSON or YAML.
Home-page: https://github.com/mzulqarnain1/Flask-YAML-Fixtures
Author: M. Zulqarnain
Author-email: zulqarnain.mailbox@gmail.com
Maintainer: M. Zulqarnain
Maintainer-email: zulqarnain.mailbox@gmail.com
License: MIT License
Platform: any
Classifier: Development Status :: 3 - Alpha
Classifier: Environment :: Web Environment
Classifier: Intended Audience :: Developers
Classifier: License :: OSI Approved :: Apache Software License
Classifier: Operating System :: OS Independent
Classifier: Programming Language :: Python :: 3
Classifier: Programming Language :: Python :: 3.8
Classifier: Programming Language :: Python :: 3.9
Classifier: Framework :: Flask
Classifier: Topic :: Internet :: WWW/HTTP :: Dynamic Content
Classifier: Topic :: Software Development :: Libraries :: Python Modules
Classifier: Topic :: Software Development :: Testing
Requires-Dist: Flask
Requires-Dist: Flask-SQLAlchemy
Requires-Dist: PyYAML (>5.1)
